sgwc/__init__.py
sgwc/setting.py
sgwc/sogou.py
sgwc/wechat.py
trash/tests/__init__.py
trash/tests/test_sougo.py
trash/tests/test_wechat.py
sgwc-2019.5.4.dist-info/LICENSE
sgwc-2019.5.4.dist-info/METADATA
sgwc-2019.5.4.dist-info/WHEEL
sgwc-2019.5.4.dist-info/top_level.txt
sgwc-2019.5.4.dist-info/RECORD
